eflips/ingest/__init__.py
eflips/ingest/base.py
eflips/ingest/data/bvg_xml.xsd
eflips/ingest/dummy.py
eflips/ingest/gtfs.py
eflips/ingest/legacy/__init__.py
eflips/ingest/legacy/bvgxml.py
eflips/ingest/legacy/vdv452/vdv2.py
eflips/ingest/legacy/xmldata/README.md
eflips/ingest/legacy/xmldata/__init__.py
eflips/ingest/legacy/xmldata/bvg_xml.py
eflips/ingest/py.typed
eflips/ingest/util.py
eflips/ingest/vdv.py
eflips/ingest/vdv452data/__init__.py
eflips/ingest/vdv452data/vdv452_v1_5.py
eflips_ingest-1.4.1.dist-info/METADATA
eflips_ingest-1.4.1.dist-info/WHEEL
eflips_ingest-1.4.1.dist-info/licenses/LICENSE.md
eflips_ingest-1.4.1.dist-info/RECORD
