Metadata-Version: 2.4
Name: eflips-ingest
Version: 1.4.1
Summary: A collection of import scripts for converting bus schedule data into the [eflips-model](https://github.com/mpm-tu-berlin/eflips-model) data format.
License: AGPL-3.0-or-later
License-File: LICENSE.md
Author: Ludger Heide
Author-email: ludger.heide@lhtechnologies.de
Requires-Python: >=3.10,<3.14
Classifier: License :: OSI Approved :: GNU Affero General Public License v3 or later (AGPLv3+)
Classifier: Programming Language :: Python :: 3
Classifier: Programming Language :: Python :: 3.10
Classifier: Programming Language :: Python :: 3.11
Classifier: Programming Language :: Python :: 3.12
Classifier: Programming Language :: Python :: 3.13
Requires-Dist: eflips-model (>=9.1.0,<11.0.0)
Requires-Dist: fire (>=0.7.0,<0.8.0)
Requires-Dist: gtfs-kit (>=12.0.0,<13.0.0)
Requires-Dist: lxml (>=5.1.0,<6.0.0)
Requires-Dist: pyproj (>=3.6.1,<4.0.0)
Requires-Dist: pytz (>=2024.1,<2025.0)
Requires-Dist: requests (>=2.31.0,<3.0.0)
Requires-Dist: xsdata[cli,lxml] (>=24.1,<25.0)
Project-URL: Homepage, https://github.com/mpm-tu-berlin/eflips-ingest
Project-URL: Repository, https://github.com/mpm-tu-berlin/eflips-ingest
